Metadata-Version: 1.1
Name: mattsimplecalculator
Version: 0.0.1
Summary: Basic calculator
Home-page:  
Author: Matt Meyer
Author-email: matt.meyer3@gmail.com
License: MIT
Keywords: calculator
Platform: UNKNOWN
Classifier: Development Status :: 3 - Alpha
Classifier: Topic :: Utilities
Classifier: License :: OSI Approved :: MIT License
